LICENSE
README.md
setup.cfg
setup.py
blockcypher/__init__.py
blockcypher/api.py
blockcypher/constants.py
blockcypher/crypto.py
blockcypher/utils.py
blockcypher_lib.egg-info/PKG-INFO
blockcypher_lib.egg-info/SOURCES.txt
blockcypher_lib.egg-info/dependency_links.txt
blockcypher_lib.egg-info/requires.txt
blockcypher_lib.egg-info/top_level.txt