Metadata-Version: 2.1
Name: blockcypher-lib
Version: 1.0.93
Summary: BlockCypher Python Library
Home-page: https://github.com/blockcypher/blockcypher-python/
Author: Michael Flaxman
Author-email: mflaxmanblockcypher@gmail.com
License: UNKNOWN
Platform: UNKNOWN
